<?xml version="1.0" encoding="utf-8" standalone="yes"?>
<Levels>
  <Level ID="1">
    <Settings>
      <GridSize x="5" y="2" />
      <CellSize x="30" y="15" />
      <StartingCell x="0" y="0" />
      <EndingCell x="4" y="0" />
    </Settings>
    <WFC>
      <Tiles>
        <Tile ID="AIR" Frequency="4">
          <Prefab Path="Prefabs/Chunks/Air" />
          <Constraints>
            <Constraint Direction="ALL">
              <Neighbours>
                <Neighbour ID="AIR" />
              </Neighbours>
            </Constraint>
            <Constraint Direction="SOUTH">
              <Neighbours>
                <Neighbour ID="GORGE" />
                <Neighbour ID="START" />
                <Neighbour ID="END" />
              </Neighbours>
            </Constraint>
          </Constraints>
        </Tile>
        <Tile ID="GORGE" Frequency="3">
          <Prefab Path="Prefabs/Chunks/Gorge" />
          <Constraints>
            <Constraint Direction="HORIZONTAL">
              <Neighbours>
                <Neighbour ID="START" />
                <Neighbour ID="END" />
                <Neighbour ID="GORGE" />
              </Neighbours>
            </Constraint>
          </Constraints>
        </Tile>
        <Tile ID="START" Frequency="1">
          <Prefab Path="Prefabs/Chunks/Start" />
          <Constraints />
        </Tile>
        <Tile ID="END" Frequency="1">
          <Prefab Path="Prefabs/Chunks/End" />
          <Constraints />
        </Tile>
      </Tiles>
    </WFC>
  </Level>
</Levels>